robinson_NLP2/__init__.py
robinson_nlp2-0.1.0.dist-info/METADATA
robinson_nlp2-0.1.0.dist-info/WHEEL
robinson_nlp2-0.1.0.dist-info/RECORD
