Metadata-Version: 2.1
Name: robinson_NLP2
Version: 0.1.0
Summary: 
Author: SterreWalta220759
Author-email: 112825711+SterreWalta220759@users.noreply.github.com
Requires-Python: >=3.9,<3.10
Classifier: Programming Language :: Python :: 3
Classifier: Programming Language :: Python :: 3.9
Requires-Dist: matplotlib (>=3.8.4,<4.0.0)
Requires-Dist: more-itertools (>=10.2.0,<11.0.0)
Requires-Dist: nltk (>=3.8.1,<4.0.0)
Requires-Dist: pandas (>=2.2.2,<3.0.0)
Requires-Dist: scikit-learn (>=1.4.2,<2.0.0)
Requires-Dist: seaborn (>=0.13.2,<0.14.0)
Requires-Dist: spacy (>=3.7.4,<4.0.0)
Requires-Dist: tensorflow (==2.10.0)
Requires-Dist: tensorflow-io-gcs-filesystem (==0.31.0)
Requires-Dist: textblob (>=0.18.0.post0,<0.19.0)
Requires-Dist: toolz (>=0.12.1,<0.13.0)
Requires-Dist: transformers (>=4.40.2,<5.0.0)
